{
  "projectMain": [
    {
      "image": "https://raw.githubusercontent.com/hagi0929/personal-website-v2/a84e72c9cff8445114a265aaf20a1e867f03a1ac/assets/projectImage/mathboard.svg",
      "title": "test",
      "description": "test description main project. ",
      "github": "https://github.com/hagi0929",
      "link": "jnjn",
      "skills": [
        "Django",
        "TypeScript",
        "SCSS",
        "HTML",
        "MySql",
        "AWS"
      ]
    },
    {
      "image": "https://raw.githubusercontent.com/hagi0929/personal-website-v2/a84e72c9cff8445114a265aaf20a1e867f03a1ac/assets/projectImage/mathboard.svg",
      "title": "sec",
      "description": "test description main project. longer deslonger deslonger deslonger deslonger deslonger deslonger deslonger deslonger deslonger deslonger des",
      "github": "https://github.com/hagi0929",
      "link": "http://www.mathboard.online/",
      "skills": [
        "Django",
        "TypeScript",
        "SCSS",
        "HTML",
        "MySql",
        "AWS"
      ]
    }
  ],
  "projectSub": [
    {
      "image": "https://raw.githubusercontent.com/hagi0929/personal-website-v2/a84e72c9cff8445114a265aaf20a1e867f03a1ac/assets/projectImage/mathboard.svg",
      "title": "auto gen test",
      "description": "hello world",
      "github": "https://github.com/hagi0929",
      "link": "http://www.google.com/",
      "skills": [
        "Django",
        "TypeScript",
        "SCSS",
        "HTML",
        "MySql",
        "AWS"
      ],
      "color": "#E91E63"
    }
  ]
}
